photosortman/__init__.py
photosortman/__main__.py
photosortman/controller_remap_dialog.py
photosortman/photoman.py
photosortman/quality_analysis.py
photosortman/assets/resources/bad.wav
photosortman/assets/resources/best.wav
photosortman/assets/resources/icon.png
photosortman/assets/resources/select.wav
photosortman/assets/resources/standar.wav
photosortman-1.0.2.dist-info/licenses/LICENSE
photosortman-1.0.2.dist-info/METADATA
photosortman-1.0.2.dist-info/WHEEL
photosortman-1.0.2.dist-info/entry_points.txt
photosortman-1.0.2.dist-info/top_level.txt
photosortman-1.0.2.dist-info/RECORD
