Metadata-Version: 2.4
Name: photosortman
Version: 1.0.2
Summary: A photo sorting tool with game controller support and AI quality analysis
Author-email: Rania Amina <me@raniaamina.id>
License: GPL-3.0-or-later
Project-URL: Homepage, https://github.com/raniaamina/photosortman
Project-URL: Repository, https://github.com/raniaamina/photosortman
Project-URL: Issues, https://github.com/raniaamina/photosortman/issues
Keywords: photo,sorting,image,quality,controller,gamepad,photography
Classifier: Development Status :: 4 - Beta
Classifier: Intended Audience :: End Users/Desktop
Classifier: License :: OSI Approved :: GNU General Public License v3 or later (GPLv3+)
Classifier: Programming Language :: Python :: 3
Classifier: Programming Language :: Python :: 3.12
Classifier: Topic :: Multimedia :: Graphics
Classifier: Topic :: Multimedia :: Graphics :: Viewers
Classifier: Operating System :: OS Independent
Requires-Python: >=3.12
License-File: LICENSE
Requires-Dist: PyQt6>=6.0.0
Requires-Dist: pygame>=2.0.0
Requires-Dist: opencv-python>=4.5.0
Requires-Dist: numpy>=1.20.0
Requires-Dist: Pillow>=9.0.0
Requires-Dist: pillow-heif>=0.10.0
Provides-Extra: gpu
Requires-Dist: cupy-cuda12x; extra == "gpu"
Dynamic: license-file
